mewbot/io/common.py
mewbot/io/desktop_notification.py
mewbot/io/http.py
mewbot/io/py.typed
mewbot/io/rss.py
mewbot/io/socket.py
mewbot_io-0.0.3.dist-info/LICENSE.md
mewbot_io-0.0.3.dist-info/METADATA
mewbot_io-0.0.3.dist-info/WHEEL
mewbot_io-0.0.3.dist-info/top_level.txt
mewbot_io-0.0.3.dist-info/RECORD
