Metadata-Version: 2.1
Name: mewbot-io
Version: 0.0.3
Summary: Lightweight, YAML-driven, text based, generic irc Bot framework
Home-page: https://github.com/mewler/mewbot
Author: Mewbot Developers (https://github.com/mewbotorg)
Author-email: mewbot@quicksilver.london
License: UNKNOWN
Project-URL: Bug Tracker, https://github.com/mewler/mewbot/issues
Platform: UNKNOWN
Classifier: Programming Language :: Python :: 3
Classifier: Operating System :: OS Independent
Classifier: License :: OSI Approved :: BSD License
Requires-Python: >=3.10
License-File: LICENSE.md
Requires-Dist: aiohttp (>=3.8.0)
Requires-Dist: feedparser (~=6.0.10)
Requires-Dist: mewbot-core (==0.0.3)
Requires-Dist: py-cord (~=2.4.1)
Requires-Dist: win10toast (~=0.9) ; sys_platform == "win32"
